odoo8_addon_l10n_fi_banks-8.0.1.0.0.99.dev5-py2.7-nspkg.pth
odoo8_addon_l10n_fi_banks-8.0.1.0.0.99.dev5.dist-info/DESCRIPTION.rst
odoo8_addon_l10n_fi_banks-8.0.1.0.0.99.dev5.dist-info/METADATA
odoo8_addon_l10n_fi_banks-8.0.1.0.0.99.dev5.dist-info/RECORD
odoo8_addon_l10n_fi_banks-8.0.1.0.0.99.dev5.dist-info/WHEEL
odoo8_addon_l10n_fi_banks-8.0.1.0.0.99.dev5.dist-info/metadata.json
odoo8_addon_l10n_fi_banks-8.0.1.0.0.99.dev5.dist-info/namespace_packages.txt
odoo8_addon_l10n_fi_banks-8.0.1.0.0.99.dev5.dist-info/top_level.txt
odoo_addons/l10n_fi_banks/README.rst
odoo_addons/l10n_fi_banks/__init__.py
odoo_addons/l10n_fi_banks/__openerp__.py
odoo_addons/l10n_fi_banks/data/res_bank.xml
odoo_addons/l10n_fi_banks/i18n/fi.po
odoo_addons/l10n_fi_banks/static/description/icon.png
